happybase_sql/__init__.py
happybase_sql/connection.py
happybase_sql/table.py
happybase_sql-0.1.0.dist-info/WHEEL
happybase_sql-0.1.0.dist-info/METADATA
happybase_sql-0.1.0.dist-info/RECORD
