Metadata-Version: 2.1
Name: happybase-sql
Version: 0.1.0
Summary: A drop-in replacement for happybase that uses an SQL backend instead of HBase.
Home-page: https://github.com/jwaterhouse/happybase-sql
License: MIT
Author: Jonathon Waterhouse
Author-email: jonathon.waterhouse@gmail.com
Requires-Python: >=2.7, !=3.0.*, !=3.1.*, !=3.2.*, !=3.3.*, !=3.4.*
Classifier: License :: OSI Approved :: MIT License
Classifier: Programming Language :: Python :: 2
Classifier: Programming Language :: Python :: 2.7
Classifier: Programming Language :: Python :: 3
Classifier: Programming Language :: Python :: 3.5
Classifier: Programming Language :: Python :: 3.6
Classifier: Programming Language :: Python :: 3.7
Classifier: Programming Language :: Python :: 3.8
Requires-Dist: psycopg2 (>=2.8,<3.0)
Requires-Dist: sqlalchemy (>=1.3,<2.0)
Project-URL: Repository, https://github.com/jwaterhouse/happybase-sql
